inaction.py
setup.py
inaction.egg-info/PKG-INFO
inaction.egg-info/SOURCES.txt
inaction.egg-info/dependency_links.txt
inaction.egg-info/requires.txt
inaction.egg-info/top_level.txt