Metadata-Version: 1.0
Name: inaction
Version: 1.0
Summary: Run specified commands while specified files changes.
Home-page: https://github.com/wonderbeyond/inaction
Author: Wonder Beyond
Author-email: wonderbeyond@gmail.com
License: UNKNOWN
Platform: UNKNOWN
